poseidon/__init__.py
poseidon/evm.py
poseidon/py.typed
poseidon/solana.py
poseidon/sui.py
poseidon/ton.py
poseidon_python-2.0.1.dist-info/LICENSE
poseidon_python-2.0.1.dist-info/METADATA
poseidon_python-2.0.1.dist-info/WHEEL
poseidon_python-2.0.1.dist-info/RECORD
