Metadata-Version: 2.3
Name: poseidon-python
Version: 2.0.1
Summary: 海神波塞冬，本工具库对常用的链上交互操作进行了模块化抽象与简洁式封装，让开发者能够轻松快速地与主流区块链网络进行交互。目前支持任意 EVM 链。
License: GPL-3.0
Keywords: blockchain,web3,ethereum,evm,tooling
Author: B1ue1nWh1te
Author-email: themagicdeepsea@gmail.com
Requires-Python: >=3.9,<4.0
Classifier: Development Status :: 4 - Beta
Classifier: Intended Audience :: Developers
Classifier: License :: OSI Approved :: GNU General Public License v3 (GPLv3)
Classifier: Natural Language :: Chinese (Simplified)
Classifier: Natural Language :: English
Classifier: Programming Language :: Python :: 3
Classifier: Programming Language :: Python :: 3.9
Classifier: Programming Language :: Python :: 3.10
Classifier: Programming Language :: Python :: 3.11
Classifier: Programming Language :: Python :: 3.12
Classifier: Programming Language :: Python :: 3.13
Requires-Dist: loguru (>=0.7.2,<0.8.0)
Requires-Dist: py-solc-x (>=2.0.3,<3.0.0)
Requires-Dist: pyevmasm (>=0.2.3,<0.3.0)
Requires-Dist: starkbank-ecdsa (>=2.2.0,<3.0.0)
Requires-Dist: web3 (>=6.20.4,<7.0.0)
Project-URL: Documentation, https://poseidon.seaeye.cn/
Project-URL: Repository, https://github.com/B1ue1nWh1te/Poseidon
